src/__init__.py
src/configurator.py
src/mokujin.py
src/tkfinder.py
src/util.py
src/test/__init__.py
src/test/test_config.py
src/test/test_tkfinder.py
src/test/test_util.py
mokujin-2.0.dist-info/LICENSE
mokujin-2.0.dist-info/METADATA
mokujin-2.0.dist-info/WHEEL
mokujin-2.0.dist-info/top_level.txt
mokujin-2.0.dist-info/RECORD
