Metadata-Version: 2.1
Name: mokujin
Version: 2.0
Summary: frame data bot for our discord channel
Home-page: https://github.com/dynazero/mokujin
Author: dynazero
Author-email: garcia.jimmyj@gmail.com
License: UNKNOWN
Platform: UNKNOWN
Classifier: Programming Language :: Python :: 3
Classifier: License :: OSI Approved :: MIT License
Classifier: Operating System :: OS Independent
Requires-Python: >=3.6
